glum_benchmarks/cli_run.py
glum_benchmarks/bench_liblinear.py
glum_benchmarks/__init__.py
glum_benchmarks/zeros_benchmark.py
glum_benchmarks/util.py
glum_benchmarks/bench_r_glmnet.py
glum_benchmarks/problems.py
glum_benchmarks/cli_analyze.py
glum_benchmarks/bench_h2o.py
glum_benchmarks/bench_orig_sklearn_fork.py
glum_benchmarks/benchmark_sparse_sandwich.py
glum_benchmarks/bench_glum.py
glum_benchmarks/benchmark_dense_sandwich.py
glum.libs/libgomp-a34b3233.so.1.0.0
glum-3.1.2.dist-info/LICENSE
glum-3.1.2.dist-info/WHEEL
glum-3.1.2.dist-info/entry_points.txt
glum-3.1.2.dist-info/top_level.txt
glum-3.1.2.dist-info/METADATA
glum-3.1.2.dist-info/RECORD
glum/_glm.py
glum/__init__.py
glum/_solvers.py
glum/_functions.cpython-313-x86_64-linux-gnu.so
glum/_link.py
glum/_util.py
glum/_distribution.py
glum/_cd_fast.cpython-313-x86_64-linux-gnu.so
glum/_glm_cv.py
