Metadata-Version: 2.1
Name: glum
Version: 3.1.2
Summary: High performance Python GLMs with all the features!
Home-page: https://github.com/Quantco/glum
Author: QuantCo, Inc.
Author-email: noreply@quantco.com
License: BSD
Classifier: Programming Language :: Python :: 3
Classifier: Programming Language :: Python :: 3.9
Classifier: Programming Language :: Python :: 3.10
Classifier: Programming Language :: Python :: 3.11
Classifier: Programming Language :: Python :: 3.12
Classifier: Programming Language :: Python :: 3.13
Requires-Python: >=3.9
License-File: LICENSE
